sparsegraph/__init__.py
sparsegraph/convert.py
sparsegraph/algorithms/__init__.py
sparsegraph/algorithms/betweenness_centrality.py
sparsegraph/algorithms/breadth_first_search.py
sparsegraph/algorithms/closeness_centrality.py
sparsegraph/algorithms/estimate_radius.py
sparsegraph/algorithms/katz_centrality.py
sparsegraph/algorithms/tests/test_betweeness_centrality.py
sparsegraph/algorithms/tests/test_closeness_centrality.py
sparsegraph/algorithms/tests/test_katz_centrality.py
sparsegraph/algorithms/tests/test_radius_diameter.py
sparsegraph/classes/__init__.py
sparsegraph/classes/sparsegraph.py
sparsegraph/classes/tests/test_sparsegraph.py
sparsegraph/generators/__init__.py
sparsegraph/generators/random.py
sparsegraph/generators/small.py
sparsegraph-0.1.0.dist-info/LICENSE
sparsegraph-0.1.0.dist-info/METADATA
sparsegraph-0.1.0.dist-info/WHEEL
sparsegraph-0.1.0.dist-info/top_level.txt
sparsegraph-0.1.0.dist-info/RECORD
