Metadata-Version: 2.1
Name: sparsegraph
Version: 0.1.0
Summary: A graph library built on top of SciPy sparse matrices.
Author-email: Gus Beringer <gusberinger@gmail.com>
Project-URL: Homepage, https://sparsegraph.com
Project-URL: Issues, https://github.com/gusberinger/sparsegraph/issues
Classifier: Programming Language :: Python :: 3
Classifier: License :: OSI Approved :: MIT License
Classifier: Operating System :: OS Independent
Requires-Python: >=3.10
License-File: LICENSE
